setup.py
datatool/__init__.py
datatool/datetime_util.py
datatool/randp.py
datatool/window_data.py
datatool.egg-info/PKG-INFO
datatool.egg-info/SOURCES.txt
datatool.egg-info/dependency_links.txt
datatool.egg-info/top_level.txt