Metadata-Version: 1.0
Name: datatool
Version: 0.0.3
Summary: simple tools for data analysis
Home-page: https://github.com/guoxiaoyong/datatool
Author: Guo Xiaoyong
Author-email: guo.xiaoyong@gmail.com
License: UNKNOWN
Platform: UNKNOWN
